aibnbclean/CleaningRecord.py
aibnbclean/GoogleAiResponse.py
aibnbclean/__init__.py
aibnbclean/add_google_ss_rows.py
aibnbclean/get_gcal_entries.py
aibnbclean/get_google_ss_cleaning_records.py
aibnbclean/get_google_ss_credentials.py
aibnbclean/get_google_ss_header_dict.py
aibnbclean/get_todoist_api.py
aibnbclean/get_todoist_project_id.py
aibnbclean/get_twilio_client.py
aibnbclean/get_webdriver.py
aibnbclean/login_airbnb.py
aibnbclean/process.py
aibnbclean/process_ab_listing.py
aibnbclean/process_home_listing.py
aibnbclean/rm_google_ss_rows.py
aibnbclean/sort_google_ss_by_column.py
aibnbclean-1.0.0.1.dist-info/METADATA
aibnbclean-1.0.0.1.dist-info/WHEEL
aibnbclean-1.0.0.1.dist-info/top_level.txt
aibnbclean-1.0.0.1.dist-info/RECORD
