Metadata-Version: 2.4
Name: aibnbclean
Version: 1.0.0.1
Summary: airbnb cleaning notification automation tool
Author-email: Erik Whitesides <eklevjer@gmail.com>
Keywords: airbnb,cleaning,automation
Classifier: Programming Language :: Python :: 3
Classifier: License :: OSI Approved :: MIT License
Classifier: Operating System :: POSIX :: Linux
Requires-Python: >=3.9
Requires-Dist: selenium==4.29.0
Requires-Dist: recurring-ical-events==3.6.0
Requires-Dist: requests==2.32.3
Requires-Dist: google-genai==1.16.1
Requires-Dist: google-api-python-client==2.170.0
Requires-Dist: twilio==9.6.2
Requires-Dist: todoist_api_python==3.1.0
